client/__init__.py
cloudpandas/__init__.py
cloudpandas-0.1.2.dist-info/LICENSE
cloudpandas-0.1.2.dist-info/METADATA
cloudpandas-0.1.2.dist-info/WHEEL
cloudpandas-0.1.2.dist-info/top_level.txt
cloudpandas-0.1.2.dist-info/RECORD
