Metadata-Version: 2.1
Name: cloudpandas
Version: 0.1.2
Summary: Client for www.cloudpandas.com API.
Home-page: https://github.com/jefalexa/cloudpandas
Author: Jeff Alexander
Author-email: admin@cloudpandas.com
License: UNKNOWN
Project-URL: Bug Tracker, https://github.com/jefalexa/cloudpandas/issues
Platform: UNKNOWN
Classifier: Programming Language :: Python :: 3
Classifier: License :: OSI Approved :: MIT License
Classifier: Operating System :: OS Independent
Requires-Python: >=3.7
License-File: LICENSE
